<?xml version="1.0" encoding="utf-8" ?>
<dwsync>
<file name=".wysiwygPro_preview_d649ac6d832b9588bf92ed68d0bc2336.php" server="cursosdeingles3ct.com/public_html/" local="131087160000000000" remote="131087160000000000" />
<file name="curso-admon-sql-server.html" server="cursosdeingles3ct.com/public_html/" local="131087160000000000" remote="131087160000000000" />
<file name="curso-de-bases-de-datos-avanzado.html" server="cursosdeingles3ct.com/public_html/" local="131087160000000000" remote="131087160000000000" />
<file name="curso-de-bases-de-datos-basico.html" server="cursosdeingles3ct.com/public_html/" local="131399753227109375" remote="131399753400000000" />
<file name="curso-de-bases-de-datos-intermedio.html" server="cursosdeingles3ct.com/public_html/" local="131087160000000000" remote="131087160000000000" />
<file name="curso-oracle-sql-plus.html" server="cursosdeingles3ct.com/public_html/" local="131087160000000000" remote="131087160000000000" />
<file name="error_log" server="cursosdeingles3ct.com/public_html/" local="131204097000000000" remote="131204097000000000" />
<file name="prueba.html" server="cursosdeingles3ct.com/public_html/" local="131087160000000000" remote="131087160000000000" />
</dwsync>